{
  "source": "foreign-affairs",
  "fetched_at": "2026-07-19T14:02:26.785739+00:00",
  "count": 20,
  "articles": [
    {
      "source": "foreign-affairs",
      "title": "A Dangerous Game in the Arctic",
      "link": "https://www.foreignaffairs.com/arctic-antarctic/dangerous-game-arctic",
      "full_text": "",
      "summary": "Trump’s demands could derail progress on allied defense.",
      "author": "",
      "published": "Fri, 17 Jul 2026 00:00:00 -0400",
      "fetched_at": "2026-07-19T14:02:26.785336+00:00"
    },
    {
      "source": "foreign-affairs",
      "title": "America’s Trillion-Dollar Failure",
      "link": "https://www.foreignaffairs.com/united-states/americas-trillion-dollar-failure-ro-khanna",
      "full_text": "",
      "summary": "The Pentagon is broken, but Congress can fix it.",
      "author": "",
      "published": "Fri, 17 Jul 2026 00:00:00 -0400",
      "fetched_at": "2026-07-19T14:02:26.785336+00:00"
    },
    {
      "source": "foreign-affairs",
      "title": "The Coming Clash Between China and Europe",
      "link": "https://www.foreignaffairs.com/china/coming-clash-between-china-and-europe",
      "full_text": "",
      "summary": "Why a trade war can’t be avoided.",
      "author": "",
      "published": "Thu, 16 Jul 2026 00:00:00 -0400",
      "fetched_at": "2026-07-19T14:02:26.785336+00:00"
    },
    {
      "source": "foreign-affairs",
      "title": "The Lost Art of Coercion",
      "link": "https://www.foreignaffairs.com/united-states/lost-art-coercion",
      "full_text": "",
      "summary": "Why Trump’s belligerence is a sign of weakness.",
      "author": "",
      "published": "Thu, 16 Jul 2026 00:00:00 -0400",
      "fetched_at": "2026-07-19T14:02:26.785336+00:00"
    },
    {
      "source": "foreign-affairs",
      "title": "The World Is Giving Up on America",
      "link": "https://www.foreignaffairs.com/united-states/world-giving-america",
      "full_text": "",
      "summary": "This time, anti-Americanism is different.",
      "author": "",
      "published": "Wed, 15 Jul 2026 00:00:00 -0400",
      "fetched_at": "2026-07-19T14:02:26.785336+00:00"
    },
    {
      "source": "foreign-affairs",
      "title": "China Is Sabotaging the World That Enables Its Rise",
      "link": "https://www.foreignaffairs.com/china/china-sabotaging-world-enables-its-rise",
      "full_text": "",
      "summary": "Beijing’s risky bet against the West.",
      "author": "",
      "published": "Wed, 15 Jul 2026 00:00:00 -0400",
      "fetched_at": "2026-07-19T14:02:26.785336+00:00"
    },
    {
      "source": "foreign-affairs",
      "title": "How China Is Winning Friends and Influencing People",
      "link": "https://www.foreignaffairs.com/china/how-china-winning-friends-and-influencing-people",
      "full_text": "",
      "summary": "Private companies are making Beijing look good in the developing world.",
      "author": "",
      "published": "Tue, 14 Jul 2026 00:00:00 -0400",
      "fetched_at": "2026-07-19T14:02:26.785336+00:00"
    },
    {
      "source": "foreign-affairs",
      "title": "Putin Will Turn a Cease-Fire Into a Weapon",
      "link": "https://www.foreignaffairs.com/russia/putin-will-turn-cease-fire-weapon",
      "full_text": "",
      "summary": "A new use for Russia’s old playbook in Ukraine.",
      "author": "",
      "published": "Tue, 14 Jul 2026 00:00:00 -0400",
      "fetched_at": "2026-07-19T14:02:26.785336+00:00"
    },
    {
      "source": "foreign-affairs",
      "title": "Senegal Is on the Brink",
      "link": "https://www.foreignaffairs.com/senegal/senegal-brink",
      "full_text": "",
      "summary": "The IMF, the World Bank, and the debt crisis that imperils West Africa.",
      "author": "",
      "published": "Mon, 13 Jul 2026 00:00:00 -0400",
      "fetched_at": "2026-07-19T14:02:26.785336+00:00"
    },
    {
      "source": "foreign-affairs",
      "title": "America and Iran’s Strange Moment of Opportunity",
      "link": "https://www.foreignaffairs.com/united-states/america-and-irans-strange-moment-opportunity",
      "full_text": "",
      "summary": "How a deadlocked conflict can pave the way for peace.",
      "author": "",
      "published": "Mon, 13 Jul 2026 00:00:00 -0400",
      "fetched_at": "2026-07-19T14:02:26.785336+00:00"
    },
    {
      "source": "foreign-affairs",
      "title": "How to Win the Defense Innovation Contest",
      "link": "https://www.foreignaffairs.com/united-states/how-win-defense-innovation-contest",
      "full_text": "",
      "summary": "America and its allies must pool their efforts.",
      "author": "",
      "published": "Fri, 10 Jul 2026 00:00:00 -0400",
      "fetched_at": "2026-07-19T14:02:26.785336+00:00"
    },
    {
      "source": "foreign-affairs",
      "title": "Iran Is Losing Iraq",
      "link": "https://www.foreignaffairs.com/iran/iran-losing-iraq",
      "full_text": "",
      "summary": "Baghdad goes its own way.",
      "author": "",
      "published": "Fri, 10 Jul 2026 00:00:00 -0400",
      "fetched_at": "2026-07-19T14:02:26.785336+00:00"
    },
    {
      "source": "foreign-affairs",
      "title": "How to Save the UN From Irrelevance",
      "link": "https://www.foreignaffairs.com/ukraine/how-save-irrelevance",
      "full_text": "",
      "summary": "Ending the peacekeeper’s paralysis.",
      "author": "",
      "published": "Thu, 09 Jul 2026 00:00:00 -0400",
      "fetched_at": "2026-07-19T14:02:26.785336+00:00"
    },
    {
      "source": "foreign-affairs",
      "title": "Trump Is Remaking Latin America",
      "link": "https://www.foreignaffairs.com/americas/trump-remaking-latin-america",
      "full_text": "",
      "summary": "The short-term results and the long-term risks of the “Donroe Doctrine.”",
      "author": "",
      "published": "Thu, 09 Jul 2026 00:00:00 -0400",
      "fetched_at": "2026-07-19T14:02:26.785336+00:00"
    },
    {
      "source": "foreign-affairs",
      "title": "Can the Private Sector Save Vietnam?",
      "link": "https://www.foreignaffairs.com/southeast-asia/can-private-sector-save-vietnam",
      "full_text": "",
      "summary": "Why the Communist Party wants business to boom.",
      "author": "",
      "published": "Wed, 08 Jul 2026 00:00:00 -0400",
      "fetched_at": "2026-07-19T14:02:26.785336+00:00"
    },
    {
      "source": "foreign-affairs",
      "title": "The Ukraine Lesson Taiwan Keeps Missing",
      "link": "https://www.foreignaffairs.com/united-states/ukraine-lesson-taiwan-keeps-missing",
      "full_text": "",
      "summary": "It’s not the drones—It’s everything around them.",
      "author": "",
      "published": "Wed, 08 Jul 2026 00:00:00 -0400",
      "fetched_at": "2026-07-19T14:02:26.785336+00:00"
    },
    {
      "source": "foreign-affairs",
      "title": "Build a Palestinian State",
      "link": "https://www.foreignaffairs.com/palestinian-territories/build-palestinian-state",
      "full_text": "",
      "summary": "Fulfill the promise of self-determination and stabilize the Middle East.",
      "author": "",
      "published": "Tue, 07 Jul 2026 00:00:00 -0400",
      "fetched_at": "2026-07-19T14:02:26.785336+00:00"
    },
    {
      "source": "foreign-affairs",
      "title": "How Europe Can Get Putin’s Attention",
      "link": "https://www.foreignaffairs.com/russia/how-europe-can-get-putins-attention",
      "full_text": "",
      "summary": "The continent must overcome its Russia predicament.",
      "author": "",
      "published": "Tue, 07 Jul 2026 00:00:00 -0400",
      "fetched_at": "2026-07-19T14:02:26.785336+00:00"
    },
    {
      "source": "foreign-affairs",
      "title": "A Better Way to Build AI",
      "link": "https://www.foreignaffairs.com/united-states/better-way-build-ai",
      "full_text": "",
      "summary": "America’s dominance depends on getting local communities on board.",
      "author": "",
      "published": "Mon, 06 Jul 2026 00:00:00 -0400",
      "fetched_at": "2026-07-19T14:02:26.785336+00:00"
    },
    {
      "source": "foreign-affairs",
      "title": "The Transatlantic Alliance Can’t Survive Without Trust",
      "link": "https://www.foreignaffairs.com/united-states/nato-transatlantic-alliance-cant-survive-without-trust",
      "full_text": "",
      "summary": "Washington dismisses NATO’s value at its own peril.",
      "author": "",
      "published": "Mon, 06 Jul 2026 00:00:00 -0400",
      "fetched_at": "2026-07-19T14:02:26.785336+00:00"
    }
  ]
}